[
  {
    "ContainingType": "WebApi.Controllers.AlbumController",
    "Method": "GetAllAlbums",
    "RelativePath": "api/Album",
    "HttpMethod": "GET",
    "IsController": true,
    "Order": 0,
    "Parameters": [],
    "ReturnTypes": []
  },
  {
    "ContainingType": "WebApi.Controllers.AlbumController",
    "Method": "AddAlbum",
    "RelativePath": "api/Album",
    "HttpMethod": "POST",
    "IsController": true,
    "Order": 0,
    "Parameters": [
      {
        "Name": "album",
        "Type": "DL.Entities.Album",
        "IsRequired": true
      }
    ],
    "ReturnTypes": []
  },
  {
    "ContainingType": "WebApi.Controllers.AlbumController",
    "Method": "GetAlbumById",
    "RelativePath": "api/Album/{id}",
    "HttpMethod": "GET",
    "IsController": true,
    "Order": 0,
    "Parameters": [
      {
        "Name": "id",
        "Type": "System.Int32",
        "IsRequired": true
      }
    ],
    "ReturnTypes": []
  },
  {
    "ContainingType": "WebApi.Controllers.AlbumController",
    "Method": "UpdateAlbum",
    "RelativePath": "api/Album/{id}",
    "HttpMethod": "PUT",
    "IsController": true,
    "Order": 0,
    "Parameters": [
      {
        "Name": "id",
        "Type": "System.Int32",
        "IsRequired": true
      },
      {
        "Name": "albumName",
        "Type": "System.String",
        "IsRequired": true
      }
    ],
    "ReturnTypes": []
  },
  {
    "ContainingType": "WebApi.Controllers.AlbumController",
    "Method": "DeleteAlbum",
    "RelativePath": "api/Album/{id}",
    "HttpMethod": "DELETE",
    "IsController": true,
    "Order": 0,
    "Parameters": [
      {
        "Name": "id",
        "Type": "System.Int32",
        "IsRequired": true
      }
    ],
    "ReturnTypes": []
  },
  {
    "ContainingType": "WebApi.Controllers.ImageController",
    "Method": "GetAllImages",
    "RelativePath": "api/Image",
    "HttpMethod": "GET",
    "IsController": true,
    "Order": 0,
    "Parameters": [],
    "ReturnTypes": []
  },
  {
    "ContainingType": "WebApi.Controllers.ImageController",
    "Method": "AddImage",
    "RelativePath": "api/Image",
    "HttpMethod": "POST",
    "IsController": true,
    "Order": 0,
    "Parameters": [
      {
        "Name": "img",
        "Type": "DL.Entities.Image",
        "IsRequired": true
      }
    ],
    "ReturnTypes": []
  },
  {
    "ContainingType": "WebApi.Controllers.ImageController",
    "Method": "GetImageById",
    "RelativePath": "api/Image/{id}",
    "HttpMethod": "GET",
    "IsController": true,
    "Order": 0,
    "Parameters": [
      {
        "Name": "id",
        "Type": "System.Int32",
        "IsRequired": true
      }
    ],
    "ReturnTypes": []
  },
  {
    "ContainingType": "WebApi.Controllers.ImageController",
    "Method": "UpdateImage",
    "RelativePath": "api/Image/{id}",
    "HttpMethod": "PUT",
    "IsController": true,
    "Order": 0,
    "Parameters": [
      {
        "Name": "id",
        "Type": "System.Int32",
        "IsRequired": true
      },
      {
        "Name": "image",
        "Type": "DL.Entities.Image",
        "IsRequired": true
      }
    ],
    "ReturnTypes": []
  },
  {
    "ContainingType": "WebApi.Controllers.ImageController",
    "Method": "DeleteImage",
    "RelativePath": "api/Image/{id}",
    "HttpMethod": "DELETE",
    "IsController": true,
    "Order": 0,
    "Parameters": [
      {
        "Name": "id",
        "Type": "System.Int32",
        "IsRequired": true
      }
    ],
    "ReturnTypes": []
  },
  {
    "ContainingType": "WebApi.Controllers.ImageController",
    "Method": "SearchImages",
    "RelativePath": "api/Image/search",
    "HttpMethod": "GET",
    "IsController": true,
    "Order": 0,
    "Parameters": [
      {
        "Name": "query",
        "Type": "System.String",
        "IsRequired": false
      }
    ],
    "ReturnTypes": []
  },
  {
    "ContainingType": "WebApi.Controllers.UploadController",
    "Method": "GetPresignedUrl",
    "RelativePath": "api/upload/presigned-url",
    "HttpMethod": "GET",
    "IsController": true,
    "Order": 0,
    "Parameters": [
      {
        "Name": "fileName",
        "Type": "System.String",
        "IsRequired": false
      },
      {
        "Name": "albumId",
        "Type": "System.Int32",
        "IsRequired": false
      },
      {
        "Name": "ownerId",
        "Type": "System.Int32",
        "IsRequired": false
      }
    ],
    "ReturnTypes": []
  },
  {
    "ContainingType": "WebApi.Controllers.UserController",
    "Method": "GetAllUsersAsync",
    "RelativePath": "api/User",
    "HttpMethod": "GET",
    "IsController": true,
    "Order": 0,
    "Parameters": [],
    "ReturnTypes": [
      {
        "Type": "System.Collections.Generic.List\u00601[[DL.Dtos.UserDto, DL, Version=1.0.0.0, Culture=neutral, PublicKeyToken=null]]",
        "MediaTypes": [
          "text/plain",
          "application/json",
          "text/json"
        ],
        "StatusCode": 200
      }
    ]
  },
  {
    "ContainingType": "WebApi.Controllers.UserController",
    "Method": "AddUserAsync",
    "RelativePath": "api/User",
    "HttpMethod": "POST",
    "IsController": true,
    "Order": 0,
    "Parameters": [
      {
        "Name": "user",
        "Type": "WebApi.Models.UserPostModel",
        "IsRequired": true
      }
    ],
    "ReturnTypes": []
  },
  {
    "ContainingType": "WebApi.Controllers.UserController",
    "Method": "GetUserByIdAsync",
    "RelativePath": "api/User/{id}",
    "HttpMethod": "GET",
    "IsController": true,
    "Order": 0,
    "Parameters": [
      {
        "Name": "id",
        "Type": "System.Int32",
        "IsRequired": true
      }
    ],
    "ReturnTypes": [
      {
        "Type": "DL.Dtos.UserDto",
        "MediaTypes": [
          "text/plain",
          "application/json",
          "text/json"
        ],
        "StatusCode": 200
      }
    ]
  },
  {
    "ContainingType": "WebApi.Controllers.UserController",
    "Method": "UpDateUserAsync",
    "RelativePath": "api/User/{id}",
    "HttpMethod": "PUT",
    "IsController": true,
    "Order": 0,
    "Parameters": [
      {
        "Name": "id",
        "Type": "System.Int32",
        "IsRequired": true
      },
      {
        "Name": "user",
        "Type": "DL.Entities.User",
        "IsRequired": true
      }
    ],
    "ReturnTypes": []
  },
  {
    "ContainingType": "WebApi.Controllers.UserController",
    "Method": "RemoveUserAsync",
    "RelativePath": "api/User/{id}",
    "HttpMethod": "DELETE",
    "IsController": true,
    "Order": 0,
    "Parameters": [
      {
        "Name": "id",
        "Type": "System.Int32",
        "IsRequired": true
      }
    ],
    "ReturnTypes": []
  },
  {
    "ContainingType": "WebApi.Controllers.UserController",
    "Method": "LoginUserAsync",
    "RelativePath": "api/User/login",
    "HttpMethod": "POST",
    "IsController": true,
    "Order": 0,
    "Parameters": [
      {
        "Name": "loginRequest",
        "Type": "WebApi.Models.LoginModel",
        "IsRequired": true
      }
    ],
    "ReturnTypes": []
  }
]